elasticsearch_test/__init__.py
elasticsearch_test_py-1.1.0.dist-info/LICENSE
elasticsearch_test_py-1.1.0.dist-info/METADATA
elasticsearch_test_py-1.1.0.dist-info/WHEEL
elasticsearch_test_py-1.1.0.dist-info/top_level.txt
elasticsearch_test_py-1.1.0.dist-info/RECORD
