Metadata-Version: 2.1
Name: elasticsearch-test-py
Version: 1.1.0
Summary: Start Elasticsearch with Python (for testing or other purposes)
Home-page: https://github.com/spraakbanken/elasticsearch-test-py
Author: Språkbanken
Author-email: maria.ohrman@gu.se
License: MIT License
Platform: UNKNOWN
Classifier: Intended Audience :: Developers
Classifier: License :: OSI Approved :: MIT License
Classifier: Operating System :: POSIX :: Linux
Classifier: Programming Language :: Python
Classifier: Programming Language :: Python :: 2
Classifier: Programming Language :: Python :: 3
Classifier: Programming Language :: Python :: 2.7
Classifier: Programming Language :: Python :: 3.4
Classifier: Programming Language :: Python :: 3.5
Classifier: Programming Language :: Python :: 3.6
Classifier: Programming Language :: Python :: 3.7
Classifier: Topic :: Database
Classifier: Topic :: Software Development
Classifier: Topic :: Software Development :: Testing
Provides-Extra: testing
Requires-Dist: tox ; extra == 'testing'
Requires-Dist: pytest ; extra == 'testing'
Requires-Dist: requests ; extra == 'testing'
Requires-Dist: coverage ; extra == 'testing'
